brcpftester
