Metadata-Version: 1.1
Name: br-cpf-tester
Version: 0.1.4
Summary: Brazilian CPF Tester
Home-page: https://github.com/Jaimenms/python-br-cpf-tester
Author: Jaime Neiva Miranda de Souza
Author-email: jaimenms@gmail.com
License: MIT
Keywords: validator cpf Brazil WTTD
Platform: UNKNOWN
Classifier: Development Status :: 3 - Alpha
Classifier: Intended Audience :: Developers
Classifier: Topic :: Software Development :: Build Tools
Classifier: License :: OSI Approved :: MIT License
Classifier: Programming Language :: Python :: 3
Classifier: Programming Language :: Python :: 3.3
Classifier: Programming Language :: Python :: 3.4
Classifier: Programming Language :: Python :: 3.5
Classifier: Programming Language :: Python :: 3.6
